{
"meta":{"test_sets":[],"test_metrics":[],"learn_metrics":[{"best_value":"Min","name":"MultiClass"}],"launch_mode":"Train","parameters":"","iteration_count":203,"learn_sets":["learn"],"name":"experiment"},
"iterations":[
{"learn":[1.872000267],"iteration":0,"passed_time":0.7059022038,"remaining_time":142.5922452},
{"learn":[1.811936625],"iteration":1,"passed_time":1.321741546,"remaining_time":132.8350254},
{"learn":[1.763627208],"iteration":2,"passed_time":1.979174284,"remaining_time":131.9449522},
{"learn":[1.722656896],"iteration":3,"passed_time":2.602621746,"remaining_time":129.4804319},
{"learn":[1.68863267],"iteration":4,"passed_time":3.23032952,"remaining_time":127.921049},
{"learn":[1.659450634],"iteration":5,"passed_time":3.891753196,"remaining_time":127.77923},
{"learn":[1.632230784],"iteration":6,"passed_time":4.533014467,"remaining_time":126.9244051},
{"learn":[1.610033657],"iteration":7,"passed_time":5.179827139,"remaining_time":126.2582865},
{"learn":[1.569795222],"iteration":8,"passed_time":5.825909564,"remaining_time":125.5807173},
{"learn":[1.542733688],"iteration":9,"passed_time":6.545492487,"remaining_time":126.328005},
{"learn":[1.523533729],"iteration":10,"passed_time":7.365130713,"remaining_time":128.5550088},
{"learn":[1.502879296],"iteration":11,"passed_time":8.156551939,"remaining_time":129.8251184},
{"learn":[1.48812784],"iteration":12,"passed_time":8.978779527,"remaining_time":131.2283162},
{"learn":[1.470440622],"iteration":13,"passed_time":9.771424092,"remaining_time":131.9142252},
{"learn":[1.450228151],"iteration":14,"passed_time":10.40528015,"remaining_time":130.4128446},
{"learn":[1.433177354],"iteration":15,"passed_time":11.02850745,"remaining_time":128.8956809},
{"learn":[1.423036827],"iteration":16,"passed_time":11.66233503,"remaining_time":127.5996656},
{"learn":[1.411791082],"iteration":17,"passed_time":12.31603364,"remaining_time":126.5814568},
{"learn":[1.402246976],"iteration":18,"passed_time":12.96155931,"remaining_time":125.5224691},
{"learn":[1.392419635],"iteration":19,"passed_time":13.59228247,"remaining_time":124.3693846},
{"learn":[1.370832695],"iteration":20,"passed_time":14.2723062,"remaining_time":123.6933204},
{"learn":[1.348559391],"iteration":21,"passed_time":14.93460758,"remaining_time":122.8710896},
{"learn":[1.34006943],"iteration":22,"passed_time":15.63637845,"remaining_time":122.3716574},
{"learn":[1.332655142],"iteration":23,"passed_time":16.25410018,"remaining_time":121.2284972},
{"learn":[1.311219206],"iteration":24,"passed_time":16.90930966,"remaining_time":120.3942848},
{"learn":[1.30502497],"iteration":25,"passed_time":17.51883431,"remaining_time":119.2628336},
{"learn":[1.29900778],"iteration":26,"passed_time":18.13000821,"remaining_time":118.1807942},
{"learn":[1.280760378],"iteration":27,"passed_time":18.75963144,"remaining_time":117.2476965},
{"learn":[1.263269612],"iteration":28,"passed_time":19.4068509,"remaining_time":116.4411054},
{"learn":[1.257559728],"iteration":29,"passed_time":20.03641549,"remaining_time":115.5433293},
{"learn":[1.233151092],"iteration":30,"passed_time":20.67550119,"remaining_time":114.715684},
{"learn":[1.218523966],"iteration":31,"passed_time":21.29626406,"remaining_time":113.8019111},
{"learn":[1.212719229],"iteration":32,"passed_time":21.93264104,"remaining_time":112.9863326},
{"learn":[1.192878065],"iteration":33,"passed_time":22.54746059,"remaining_time":112.0741424},
{"learn":[1.188081736],"iteration":34,"passed_time":23.17082,"remaining_time":111.219936},
{"learn":[1.167678832],"iteration":35,"passed_time":23.85084507,"remaining_time":110.6414202},
{"learn":[1.162264303],"iteration":36,"passed_time":24.4647502,"remaining_time":109.7607712},
{"learn":[1.156241425],"iteration":37,"passed_time":25.22227839,"remaining_time":109.5177877},
{"learn":[1.151709314],"iteration":38,"passed_time":25.87415807,"remaining_time":108.8041519},
{"learn":[1.142144819],"iteration":39,"passed_time":26.50544416,"remaining_time":108.0096849},
{"learn":[1.127728128],"iteration":40,"passed_time":27.12105011,"remaining_time":107.1612224},
{"learn":[1.123881844],"iteration":41,"passed_time":27.7573878,"remaining_time":106.4033199},
{"learn":[1.111918448],"iteration":42,"passed_time":28.40974905,"remaining_time":105.7106941},
{"learn":[1.107167091],"iteration":43,"passed_time":29.10355206,"remaining_time":105.169654},
{"learn":[1.084544245],"iteration":44,"passed_time":29.80434705,"remaining_time":104.6463741},
{"learn":[1.0646728],"iteration":45,"passed_time":30.48290494,"remaining_time":104.0394799},
{"learn":[1.056751184],"iteration":46,"passed_time":31.18476671,"remaining_time":103.5068853},
{"learn":[1.051310814],"iteration":47,"passed_time":31.93050826,"remaining_time":103.1089329},
{"learn":[1.044312937],"iteration":48,"passed_time":32.64710862,"remaining_time":102.6051985},
{"learn":[1.041595293],"iteration":49,"passed_time":33.38441236,"remaining_time":102.1563018},
{"learn":[1.02735413],"iteration":50,"passed_time":34.08147825,"remaining_time":101.5761705},
{"learn":[1.009986637],"iteration":51,"passed_time":34.79625919,"remaining_time":101.0429834},
{"learn":[1.001646051],"iteration":52,"passed_time":35.42909934,"remaining_time":100.2710359},
{"learn":[0.9856797126],"iteration":53,"passed_time":36.11446621,"remaining_time":99.64917529},
{"learn":[0.9826399907],"iteration":54,"passed_time":36.88660981,"remaining_time":99.25851367},
{"learn":[0.9799328229],"iteration":55,"passed_time":37.82091951,"remaining_time":99.27991372},
{"learn":[0.9643959587],"iteration":56,"passed_time":38.76919486,"remaining_time":99.30355175},
{"learn":[0.9500462413],"iteration":57,"passed_time":39.63938688,"remaining_time":99.0984672},
{"learn":[0.9442276951],"iteration":58,"passed_time":40.40492626,"remaining_time":98.61541326},
{"learn":[0.9408276488],"iteration":59,"passed_time":41.16250852,"remaining_time":98.10397863},
{"learn":[0.9363086965],"iteration":60,"passed_time":41.91914982,"remaining_time":97.58228319},
{"learn":[0.9240843593],"iteration":61,"passed_time":42.6026636,"remaining_time":96.88670271},
{"learn":[0.9211560142],"iteration":62,"passed_time":43.27379615,"remaining_time":96.16399144},
{"learn":[0.9082502641],"iteration":63,"passed_time":43.94604369,"remaining_time":95.44531364},
{"learn":[0.9014076928],"iteration":64,"passed_time":44.63428046,"remaining_time":94.76201083},
{"learn":[0.8939946075],"iteration":65,"passed_time":45.33648957,"remaining_time":94.10756167},
{"learn":[0.8879750204],"iteration":66,"passed_time":45.98758448,"remaining_time":93.34793267},
{"learn":[0.884888089],"iteration":67,"passed_time":46.61947329,"remaining_time":92.55336609},
{"learn":[0.8770910151],"iteration":68,"passed_time":47.27550663,"remaining_time":91.81040419},
{"learn":[0.8671305527],"iteration":69,"passed_time":47.92066939,"remaining_time":91.04927184},
{"learn":[0.8633806995],"iteration":70,"passed_time":48.63912761,"remaining_time":90.42767387},
{"learn":[0.8582942274],"iteration":71,"passed_time":49.33959671,"remaining_time":89.77065513},
{"learn":[0.8522122817],"iteration":72,"passed_time":50.01508072,"remaining_time":89.06795196},
{"learn":[0.8396489525],"iteration":73,"passed_time":50.73900926,"remaining_time":88.45043506},
{"learn":[0.835221509],"iteration":74,"passed_time":51.41407416,"remaining_time":87.74668656},
{"learn":[0.8322871544],"iteration":75,"passed_time":52.0988154,"remaining_time":87.05986257},
{"learn":[0.8295808274],"iteration":76,"passed_time":52.78327438,"remaining_time":86.3726308},
{"learn":[0.8271714324],"iteration":77,"passed_time":53.48873269,"remaining_time":85.7191229},
{"learn":[0.8194323767],"iteration":78,"passed_time":54.17461241,"remaining_time":85.03356885},
{"learn":[0.8140004185],"iteration":79,"passed_time":54.81227786,"remaining_time":84.27387721},
{"learn":[0.8095136657],"iteration":80,"passed_time":55.41209789,"remaining_time":83.46019682},
{"learn":[0.8017006259],"iteration":81,"passed_time":56.06247694,"remaining_time":82.72633793},
{"learn":[0.7919789314],"iteration":82,"passed_time":56.69632019,"remaining_time":81.9705834},
{"learn":[0.7851028302],"iteration":83,"passed_time":57.37657059,"remaining_time":81.283475},
{"learn":[0.7773120996],"iteration":84,"passed_time":57.98885904,"remaining_time":80.50218078},
{"learn":[0.7751518454],"iteration":85,"passed_time":58.6819413,"remaining_time":79.8347341},
{"learn":[0.7705556748],"iteration":86,"passed_time":59.33647105,"remaining_time":79.11529474},
{"learn":[0.7691512681],"iteration":87,"passed_time":59.98344056,"remaining_time":78.38745073},
{"learn":[0.7659771631],"iteration":88,"passed_time":60.59695081,"remaining_time":77.61856621},
{"learn":[0.7627795622],"iteration":89,"passed_time":61.27251487,"remaining_time":76.93104645},
{"learn":[0.7603465284],"iteration":90,"passed_time":61.92882165,"remaining_time":76.22008819},
{"learn":[0.7569822205],"iteration":91,"passed_time":62.5650272,"remaining_time":75.48606543},
{"learn":[0.7539561764],"iteration":92,"passed_time":63.23124092,"remaining_time":74.7896398},
{"learn":[0.7471598707],"iteration":93,"passed_time":63.84110149,"remaining_time":74.0285113},
{"learn":[0.7416315045],"iteration":94,"passed_time":64.49629791,"remaining_time":73.3221071},
{"learn":[0.7343313224],"iteration":95,"passed_time":65.15058241,"remaining_time":72.61575331},
{"learn":[0.7317023793],"iteration":96,"passed_time":65.80882729,"remaining_time":71.91480096},
{"learn":[0.7281947978],"iteration":97,"passed_time":66.4622632,"remaining_time":71.20956771},
{"learn":[0.7271509374],"iteration":98,"passed_time":67.28988717,"remaining_time":70.68836632},
{"learn":[0.7245564166],"iteration":99,"passed_time":68.07201854,"remaining_time":70.1141791},
{"learn":[0.7216812238],"iteration":100,"passed_time":68.80581339,"remaining_time":69.48705907},
{"learn":[0.717336862],"iteration":101,"passed_time":69.64323109,"remaining_time":68.96045431},
{"learn":[0.7119275911],"iteration":102,"passed_time":70.35413525,"remaining_time":68.30498568},
{"learn":[0.7100287753],"iteration":103,"passed_time":71.02054849,"remaining_time":67.60609905},
{"learn":[0.7073100857],"iteration":104,"passed_time":71.67099329,"remaining_time":66.89292707},
{"learn":[0.7048892827],"iteration":105,"passed_time":72.33312735,"remaining_time":66.19163541},
{"learn":[0.7030536203],"iteration":106,"passed_time":72.99220167,"remaining_time":65.48833047},
{"learn":[0.6915037762],"iteration":107,"passed_time":73.67699371,"remaining_time":64.80846669},
{"learn":[0.688779098],"iteration":108,"passed_time":74.30570038,"remaining_time":64.08014528},
{"learn":[0.6829176814],"iteration":109,"passed_time":74.95607812,"remaining_time":63.37195695},
{"learn":[0.6806968688],"iteration":110,"passed_time":75.68105264,"remaining_time":62.72663823},
{"learn":[0.672549983],"iteration":111,"passed_time":76.33563394,"remaining_time":62.02270257},
{"learn":[0.6627783777],"iteration":112,"passed_time":77.01032696,"remaining_time":61.33565864},
{"learn":[0.660334022],"iteration":113,"passed_time":77.62627838,"remaining_time":60.60297172},
{"learn":[0.6578202632],"iteration":114,"passed_time":78.23211795,"remaining_time":59.86457721},
{"learn":[0.6549951497],"iteration":115,"passed_time":78.86124277,"remaining_time":59.14593208},
{"learn":[0.6476199794],"iteration":116,"passed_time":79.52113236,"remaining_time":58.45143062},
{"learn":[0.6387165494],"iteration":117,"passed_time":80.14653225,"remaining_time":57.73267154},
{"learn":[0.6361301805],"iteration":118,"passed_time":80.81056602,"remaining_time":57.04275248},
{"learn":[0.6342941992],"iteration":119,"passed_time":81.40927456,"remaining_time":56.30808157},
{"learn":[0.6281206804],"iteration":120,"passed_time":82.05831867,"remaining_time":55.60976968},
{"learn":[0.6226704504],"iteration":121,"passed_time":82.69141783,"remaining_time":54.90167905},
{"learn":[0.6207414232],"iteration":122,"passed_time":83.3332881,"remaining_time":54.20051259},
{"learn":[0.6185385016],"iteration":123,"passed_time":83.98642529,"remaining_time":53.50748063},
{"learn":[0.6089485871],"iteration":124,"passed_time":84.66161309,"remaining_time":52.82884657},
{"learn":[0.6069722746],"iteration":125,"passed_time":85.30809779,"remaining_time":52.13272642},
{"learn":[0.5987360733],"iteration":126,"passed_time":85.95516057,"remaining_time":51.43773389},
{"learn":[0.5971613752],"iteration":127,"passed_time":86.60714112,"remaining_time":50.74637175},
{"learn":[0.5954881098],"iteration":128,"passed_time":87.35098086,"remaining_time":50.1083146},
{"learn":[0.5937367182],"iteration":129,"passed_time":88.03960058,"remaining_time":49.43762187},
{"learn":[0.5922723533],"iteration":130,"passed_time":88.78209382,"remaining_time":48.79626531},
{"learn":[0.5869734803],"iteration":131,"passed_time":89.40293924,"remaining_time":48.08794459},
{"learn":[0.581252913],"iteration":132,"passed_time":90.06402281,"remaining_time":47.40211727},
{"learn":[0.5795029213],"iteration":133,"passed_time":90.74038161,"remaining_time":46.72452486},
{"learn":[0.5777405555],"iteration":134,"passed_time":91.39121269,"remaining_time":46.03409232},
{"learn":[0.5680100607],"iteration":135,"passed_time":92.10245739,"remaining_time":45.37400474},
{"learn":[0.5662328665],"iteration":136,"passed_time":92.7753529,"remaining_time":44.69469556},
{"learn":[0.5636885371],"iteration":137,"passed_time":93.47862266,"remaining_time":44.02978604},
{"learn":[0.5581189081],"iteration":138,"passed_time":94.1682075,"remaining_time":43.3580236},
{"learn":[0.5563335894],"iteration":139,"passed_time":94.92834314,"remaining_time":42.71775441},
{"learn":[0.5549601319],"iteration":140,"passed_time":95.63562339,"remaining_time":42.05254362},
{"learn":[0.5534242913],"iteration":141,"passed_time":96.40787751,"remaining_time":41.41465161},
{"learn":[0.5519527839],"iteration":142,"passed_time":97.22920949,"remaining_time":40.79547251},
{"learn":[0.5462755525],"iteration":143,"passed_time":98.04295834,"remaining_time":40.17037877},
{"learn":[0.5392642194],"iteration":144,"passed_time":98.80316484,"remaining_time":39.52126593},
{"learn":[0.5336058743],"iteration":145,"passed_time":99.67474526,"remaining_time":38.91411288},
{"learn":[0.5316576583],"iteration":146,"passed_time":100.3621256,"remaining_time":38.2331907},
{"learn":[0.5279761993],"iteration":147,"passed_time":101.1126839,"remaining_time":37.57565955},
{"learn":[0.523839348],"iteration":148,"passed_time":101.7593739,"remaining_time":36.87923617},
{"learn":[0.5222138156],"iteration":149,"passed_time":102.4586124,"remaining_time":36.20204306},
{"learn":[0.5203734573],"iteration":150,"passed_time":103.0959327,"remaining_time":35.50323512},
{"learn":[0.5152940125],"iteration":151,"passed_time":103.7597215,"remaining_time":34.81411707},
{"learn":[0.5074328162],"iteration":152,"passed_time":104.445306,"remaining_time":34.13245293},
{"learn":[0.5056865511],"iteration":153,"passed_time":105.1241683,"remaining_time":33.44859899},
{"learn":[0.4980118225],"iteration":154,"passed_time":105.7744256,"remaining_time":32.75595116},
{"learn":[0.4964158253],"iteration":155,"passed_time":106.3941232,"remaining_time":32.05463968},
{"learn":[0.4952476845],"iteration":156,"passed_time":107.0159818,"remaining_time":31.35500105},
{"learn":[0.490433184],"iteration":157,"passed_time":107.6673184,"remaining_time":30.66474259},
{"learn":[0.489211738],"iteration":158,"passed_time":108.2912917,"remaining_time":29.96740149},
{"learn":[0.4850870061],"iteration":159,"passed_time":108.9660622,"remaining_time":29.28462922},
{"learn":[0.4836643974],"iteration":160,"passed_time":109.5862398,"remaining_time":28.58771473},
{"learn":[0.4822683927],"iteration":161,"passed_time":110.2540178,"remaining_time":27.90379462},
{"learn":[0.4810134529],"iteration":162,"passed_time":110.8975981,"remaining_time":27.2141345},
{"learn":[0.4781576896],"iteration":163,"passed_time":111.5158814,"remaining_time":26.51902057},
{"learn":[0.4747542326],"iteration":164,"passed_time":112.1937097,"remaining_time":25.83855131},
{"learn":[0.473384402],"iteration":165,"passed_time":112.8388985,"remaining_time":25.15083882},
{"learn":[0.4719003458],"iteration":166,"passed_time":113.4273972,"remaining_time":24.45141496},
{"learn":[0.4674832136],"iteration":167,"passed_time":114.1030987,"remaining_time":23.7714789},
{"learn":[0.4660542243],"iteration":168,"passed_time":114.7231863,"remaining_time":23.08040434},
{"learn":[0.4647524967],"iteration":169,"passed_time":115.3512451,"remaining_time":22.39171229},
{"learn":[0.4644473188],"iteration":170,"passed_time":115.4086598,"remaining_time":21.59694219},
{"learn":[0.4573680024],"iteration":171,"passed_time":116.0502274,"remaining_time":20.91602935},
{"learn":[0.451408004],"iteration":172,"passed_time":116.7187219,"remaining_time":20.2402408},
{"learn":[0.4504754599],"iteration":173,"passed_time":117.384,"remaining_time":19.56399999},
{"learn":[0.4478349415],"iteration":174,"passed_time":118.0696633,"remaining_time":18.89114613},
{"learn":[0.4468292867],"iteration":175,"passed_time":118.6948787,"remaining_time":18.20887343},
{"learn":[0.4428245352],"iteration":176,"passed_time":119.3566013,"remaining_time":17.5326081},
{"learn":[0.4363971215],"iteration":177,"passed_time":120.0307977,"remaining_time":16.85825811},
{"learn":[0.4308318506],"iteration":178,"passed_time":120.6627867,"remaining_time":16.17825073},
{"learn":[0.4296114746],"iteration":179,"passed_time":121.3244132,"remaining_time":15.50256391},
{"learn":[0.4286737063],"iteration":180,"passed_time":121.9475452,"remaining_time":14.82235356},
{"learn":[0.4270268822],"iteration":181,"passed_time":122.6148146,"remaining_time":14.14786322},
{"learn":[0.4257066696],"iteration":182,"passed_time":123.2658863,"remaining_time":13.47168156},
{"learn":[0.4244890296],"iteration":183,"passed_time":123.9304287,"remaining_time":12.79716384},
{"learn":[0.4204240352],"iteration":184,"passed_time":124.5689896,"remaining_time":12.12022602},
{"learn":[0.4193256582],"iteration":185,"passed_time":125.2573649,"remaining_time":11.44825378},
{"learn":[0.4181018436],"iteration":186,"passed_time":125.9413739,"remaining_time":10.77573253},
{"learn":[0.4140334805],"iteration":187,"passed_time":126.8497552,"remaining_time":10.1209911},
{"learn":[0.409561008],"iteration":188,"passed_time":127.6815147,"remaining_time":9.457889981},
{"learn":[0.4081742162],"iteration":189,"passed_time":128.4514696,"remaining_time":8.788784765},
{"learn":[0.4072251415],"iteration":190,"passed_time":129.19721,"remaining_time":8.117102201},
{"learn":[0.4059755813],"iteration":191,"passed_time":129.9288182,"remaining_time":7.443838545},
{"learn":[0.4015209864],"iteration":192,"passed_time":130.6269632,"remaining_time":6.768236435},
{"learn":[0.3997596575],"iteration":193,"passed_time":131.3395785,"remaining_time":6.093073231},
{"learn":[0.3959502749],"iteration":194,"passed_time":132.1039001,"remaining_time":5.419647184},
{"learn":[0.3919277624],"iteration":195,"passed_time":132.8171649,"remaining_time":4.743470174},
{"learn":[0.3883152548],"iteration":196,"passed_time":133.5060508,"remaining_time":4.066174136},
{"learn":[0.3872370828],"iteration":197,"passed_time":134.2291362,"remaining_time":3.389624651},
{"learn":[0.3841017426],"iteration":198,"passed_time":134.9324115,"remaining_time":2.712209276},
{"learn":[0.380345778],"iteration":199,"passed_time":135.6934159,"remaining_time":2.035401239},
{"learn":[0.3790978889],"iteration":200,"passed_time":136.3581456,"remaining_time":1.356797468},
{"learn":[0.3754684823],"iteration":201,"passed_time":137.040033,"remaining_time":0.6784160049},
{"learn":[0.3745423202],"iteration":202,"passed_time":137.7448261,"remaining_time":0}
]}